Metadata-Version: 2.1
Name: kuminsight
Version: 0.0.1
Summary: NLP Toolkit For Thai Language
Author: SAI2-EXP
License: UNKNOWN
Platform: UNKNOWN
License-File: license.txt
